midrasai/__init__.py
midrasai/_abc.py
midrasai/_constants.py
midrasai/cli.py
midrasai/client/__init__.py
midrasai/client/main.py
midrasai/local/__init__.py
midrasai/local/main.py
midrasai/local/server.py
midrasai/types.py
midrasai/vectordb/__init__.py
midrasai/vectordb/_qdrant.py
midrasai-0.1.5.dist-info/LICENSE
midrasai-0.1.5.dist-info/METADATA
midrasai-0.1.5.dist-info/WHEEL
midrasai-0.1.5.dist-info/entry_points.txt
midrasai-0.1.5.dist-info/RECORD
