Metadata-Version: 2.1
Name: midrasai
Version: 0.1.5
Summary: A simple framework for multimodal RAG
Author: ajac-zero
Author-email: ajcardoza2000@gmail.com
Requires-Python: >=3.10,<4.0
Classifier: Programming Language :: Python :: 3
Classifier: Programming Language :: Python :: 3.10
Classifier: Programming Language :: Python :: 3.11
Classifier: Programming Language :: Python :: 3.12
Provides-Extra: local
Requires-Dist: colpali-engine (>=0.3.1,<0.4.0) ; extra == "local"
Requires-Dist: fastapi[standard] (>=0,<1) ; extra == "local"
Requires-Dist: huggingface-hub[cli] (>=0,<1) ; extra == "local"
Requires-Dist: pdf2image (>=1.17.0,<2.0.0)
Requires-Dist: pillow (>=10,<11) ; extra == "local"
Requires-Dist: qdrant-client (>=1.11.1,<2.0.0)
Requires-Dist: typer (>=0.12.5,<0.13.0)
